jp2_remediator/__init__.py
jp2_remediator/box_reader.py
jp2_remediator/box_reader_factory.py
jp2_remediator/jp2_result.py
jp2_remediator/main.py
jp2_remediator/processor.py
jp2_remediator/tests/__init__.py
jp2_remediator/tests/integration/test_aws_connection.py
jp2_remediator/tests/unit/test_box_reader.py
jp2_remediator/tests/unit/test_jp2_result.py
jp2_remediator/tests/unit/test_processor.py
jp2_remediator-1.1.0.dist-info/LICENSE
jp2_remediator-1.1.0.dist-info/METADATA
jp2_remediator-1.1.0.dist-info/WHEEL
jp2_remediator-1.1.0.dist-info/top_level.txt
jp2_remediator-1.1.0.dist-info/RECORD
