Metadata-Version: 2.2
Name: jp2_remediator
Version: 1.1.0
Summary: A module to validate jp2images
Author-email: Kim Pham <kimpham54@gmail.com>, Andrew Woods <andrew_woods@harvard.edu>
Project-URL: Homepage, https://github.com/harvard-lts/jp2_remediator
Project-URL: Issues, https://github.com/harvard-lts/jp2_remediator/issues
Classifier: Programming Language :: Python :: 3
Classifier: License :: OSI Approved :: Apache Software License
Classifier: Operating System :: OS Independent
Requires-Python: >=3.10
License-File: LICENSE
